{
  "deals": [
    {
      "id": "community:13eaf5c3-15cd-4510-9727-16ff01027b1b",
      "submissionId": "13eaf5c3-15cd-4510-9727-16ff01027b1b",
      "brand": "Instagram",
      "logo": "🎭",
      "title": "Instagram Deal",
      "description": "📨 Von der Community eingereicht. Bitte Link, Ort und Ablauf prüfen, bevor der Deal live geht.",
      "type": "rabatt",
      "category": "kultur",
      "source": "Community Submission",
      "originSource": "community-submission",
      "url": "https://www.instagram.com/p/DXNczVNjLG7/",
      "expires": "",
      "distance": "Bitte prüfen",
      "hot": false,
      "isNew": true,
      "votes": 1,
      "priority": 4,
      "qualityScore": 0,
      "pubDate": "2026-04-26T06:20:26.432Z",
      "pubDateSource": "communitySubmission",
      "submittedAt": "2026-04-26T06:20:26.432Z",
      "missingFields": [
        "Ablauf"
      ]
    },
    {
      "id": "community:df44892f-2705-40e0-aea7-ce6c921c1b82",
      "submissionId": "df44892f-2705-40e0-aea7-ce6c921c1b82",
      "brand": "Community Fund",
      "logo": "🔗",
      "title": "Gratis Matcha Latte",
      "description": "📨 Von der Community eingereicht. Bitte Link, Ort und Ablauf prüfen, bevor der Deal live geht.",
      "type": "rabatt",
      "category": "wien",
      "source": "Community Submission",
      "originSource": "community-submission",
      "url": "https://example.com/",
      "expires": "",
      "distance": "Bitte prüfen",
      "hot": false,
      "isNew": true,
      "votes": 1,
      "priority": 4,
      "qualityScore": 0,
      "pubDate": "2026-06-24T17:24:07.168Z",
      "pubDateSource": "communitySubmission",
      "submittedAt": "2026-06-24T17:24:07.168Z",
      "missingFields": [
        "Ablauf"
      ]
    },
    {
      "id": "community:3ba1dda4-3044-4902-8f03-50abd022e3d2",
      "submissionId": "3ba1dda4-3044-4902-8f03-50abd022e3d2",
      "brand": "Community Fund",
      "logo": "🔗",
      "title": "Gratis Matcha Latte Test",
      "description": "📨 Von der Community eingereicht. Bitte Link, Ort und Ablauf prüfen, bevor der Deal live geht.",
      "type": "rabatt",
      "category": "wien",
      "source": "Community Submission",
      "originSource": "community-submission",
      "url": "https://example.com/",
      "expires": "",
      "distance": "Bitte prüfen",
      "hot": false,
      "isNew": true,
      "votes": 1,
      "priority": 4,
      "qualityScore": 0,
      "pubDate": "2026-06-24T17:24:07.168Z",
      "pubDateSource": "communitySubmission",
      "submittedAt": "2026-06-24T17:24:07.168Z",
      "missingFields": [
        "Ablauf"
      ]
    },
    {
      "id": "community:90997ece-3401-4d47-b979-566ce435ab58",
      "submissionId": "90997ece-3401-4d47-b979-566ce435ab58",
      "brand": "Community Fund",
      "logo": "🔗",
      "title": "Gratis Matcha Latte Test",
      "description": "📨 Von der Community eingereicht. Bitte Link, Ort und Ablauf prüfen, bevor der Deal live geht.",
      "type": "rabatt",
      "category": "wien",
      "source": "Community Submission",
      "originSource": "community-submission",
      "url": "https://example.com/",
      "expires": "",
      "distance": "Bitte prüfen",
      "hot": false,
      "isNew": true,
      "votes": 1,
      "priority": 4,
      "qualityScore": 0,
      "pubDate": "2026-06-24T17:24:07.168Z",
      "pubDateSource": "communitySubmission",
      "submittedAt": "2026-06-24T17:24:07.168Z",
      "missingFields": [
        "Ablauf"
      ]
    },
    {
      "id": "community:F148DBC4-BB7C-4B3F-8632-5662BF11CE30",
      "submissionId": "F148DBC4-BB7C-4B3F-8632-5662BF11CE30",
      "brand": "Community Fund",
      "logo": "🔗",
      "title": "Gratis Eis",
      "description": "📨 Von der Community eingereicht. Bitte Link, Ort und Ablauf prüfen, bevor der Deal live geht.",
      "type": "rabatt",
      "category": "wien",
      "source": "Community Submission",
      "originSource": "community-submission",
      "url": "https://www.instagram.com/p/DYrHeIIDQRq/?igsh=Nnd0ZHhtOG9kNHNo",
      "expires": "",
      "distance": "Bitte prüfen",
      "hot": false,
      "isNew": true,
      "votes": 1,
      "priority": 4,
      "qualityScore": 0,
      "pubDate": "2026-06-24T17:24:07.168Z",
      "pubDateSource": "communitySubmission",
      "submittedAt": "2026-06-24T17:24:07.168Z",
      "missingFields": [
        "Ablauf"
      ]
    },
    {
      "id": "community:a8bd13cc-99b5-4917-a17f-64bb57a61e8f",
      "submissionId": "a8bd13cc-99b5-4917-a17f-64bb57a61e8f",
      "brand": "Community Fund",
      "logo": "🔗",
      "title": "Slack Zustellung Test",
      "description": "📨 Von der Community eingereicht. Bitte Link, Ort und Ablauf prüfen, bevor der Deal live geht.",
      "type": "rabatt",
      "category": "wien",
      "source": "Community Submission",
      "originSource": "community-submission",
      "url": "https://example.com/",
      "expires": "",
      "distance": "Bitte prüfen",
      "hot": false,
      "isNew": true,
      "votes": 1,
      "priority": 4,
      "qualityScore": 0,
      "pubDate": "2026-06-24T17:24:07.168Z",
      "pubDateSource": "communitySubmission",
      "submittedAt": "2026-06-24T17:24:07.168Z",
      "missingFields": [
        "Ablauf"
      ]
    },
    {
      "id": "community:dc4ebe77-1553-4999-89f9-236150116c72",
      "submissionId": "dc4ebe77-1553-4999-89f9-236150116c72",
      "brand": "Community Fund",
      "logo": "🔗",
      "title": "Slack Webhook Test",
      "description": "📨 Von der Community eingereicht. Bitte Link, Ort und Ablauf prüfen, bevor der Deal live geht.",
      "type": "rabatt",
      "category": "wien",
      "source": "Community Submission",
      "originSource": "community-submission",
      "url": "https://example.com/",
      "expires": "",
      "distance": "Bitte prüfen",
      "hot": false,
      "isNew": true,
      "votes": 1,
      "priority": 4,
      "qualityScore": 0,
      "pubDate": "2026-06-24T17:24:07.168Z",
      "pubDateSource": "communitySubmission",
      "submittedAt": "2026-06-24T17:24:07.168Z",
      "missingFields": [
        "Ablauf"
      ]
    },
    {
      "id": "community:C4435F8E-B47F-4279-8D39-E0F2F21579D3",
      "submissionId": "C4435F8E-B47F-4279-8D39-E0F2F21579D3",
      "brand": "Community Fund",
      "logo": "🔗",
      "title": "2€ Tiramisu + 2 Monate Gratis Neotatse Code: foodiewien2m",
      "description": "📨 Von der Community eingereicht. Bitte Link, Ort und Ablauf prüfen, bevor der Deal live geht.",
      "type": "rabatt",
      "category": "wien",
      "source": "Community Submission",
      "originSource": "community-submission",
      "url": "https://www.instagram.com/reel/DYjgWxeoBuP/?igsh=cTFiNjlnNmw3OGJx",
      "expires": "",
      "distance": "Bitte prüfen",
      "hot": false,
      "isNew": true,
      "votes": 1,
      "priority": 4,
      "qualityScore": 0,
      "pubDate": "2026-06-24T17:24:07.168Z",
      "pubDateSource": "communitySubmission",
      "submittedAt": "2026-06-24T17:24:07.168Z",
      "missingFields": [
        "Ablauf"
      ]
    },
    {
      "id": "community:f931ee87-88f5-42c3-9add-93683ce85c52",
      "submissionId": "f931ee87-88f5-42c3-9add-93683ce85c52",
      "brand": "Ikea",
      "logo": "🔗",
      "title": "Sale -60%",
      "description": "📨 Von der Community eingereicht. Bitte Link, Ort und Ablauf prüfen, bevor der Deal live geht.",
      "type": "rabatt",
      "category": "wien",
      "source": "Community Submission",
      "originSource": "community-submission",
      "url": "https://www.instagram.com/p/DZU4kJVDL9O/?igsh=MWZzczhrdDZ4b3luaw==",
      "expires": "",
      "distance": "Wien",
      "hot": false,
      "isNew": true,
      "votes": 1,
      "priority": 4,
      "qualityScore": 0,
      "pubDate": "2026-06-08T17:29:28.299Z",
      "pubDateSource": "communitySubmission",
      "submittedAt": "2026-06-08T17:29:28.299Z",
      "missingFields": [
        "Ablauf"
      ]
    },
    {
      "id": "community:7b2a75f7-9e73-41c8-b9d5-886655c42bd7",
      "submissionId": "7b2a75f7-9e73-41c8-b9d5-886655c42bd7",
      "brand": "Foodora",
      "logo": "🔗",
      "title": "-60% Rabatt",
      "description": "📨 Von der Community eingereicht. Bitte Link, Ort und Ablauf prüfen, bevor der Deal live geht.",
      "type": "rabatt",
      "category": "wien",
      "source": "Community Submission",
      "originSource": "community-submission",
      "url": "https://www.instagram.com/p/DZM7iAcjBBq/?igsh=djl2bHhscXZldHl1",
      "expires": "",
      "distance": "Wien",
      "hot": false,
      "isNew": true,
      "votes": 1,
      "priority": 4,
      "qualityScore": 0,
      "pubDate": "2026-06-07T21:29:09.444Z",
      "pubDateSource": "communitySubmission",
      "submittedAt": "2026-06-07T21:29:09.444Z",
      "missingFields": [
        "Ablauf"
      ]
    },
    {
      "id": "community:41aa7928-48b2-4ef1-b570-b67f3e5d1e3c",
      "submissionId": "41aa7928-48b2-4ef1-b570-b67f3e5d1e3c",
      "brand": "Dahab Döner",
      "logo": "🔗",
      "title": "1+1 Gratis Döner",
      "description": "Wagramerstraße 126 1.6. und 3.6.",
      "type": "rabatt",
      "category": "wien",
      "source": "Community Submission",
      "originSource": "community-submission",
      "url": "https://www.instagram.com/reel/DY-YyjHuOqo/?igsh=MXZlenh4bjhmaGx3bQ==",
      "expires": "",
      "distance": "Wien",
      "hot": false,
      "isNew": true,
      "votes": 1,
      "priority": 4,
      "qualityScore": 0,
      "pubDate": "2026-06-01T07:09:36.318Z",
      "pubDateSource": "communitySubmission",
      "submittedAt": "2026-06-01T07:09:36.318Z",
      "missingFields": [
        "Ablauf"
      ]
    },
    {
      "id": "community:7c8099e2-675d-4216-be95-cb79c59194b0",
      "submissionId": "7c8099e2-675d-4216-be95-cb79c59194b0",
      "brand": "Vijomc",
      "logo": "🎭",
      "title": "Vijomc Deal",
      "description": "Von der Community geteilter Vijomc-Deal. Bitte Details direkt im Link prüfen.",
      "type": "rabatt",
      "category": "kultur",
      "source": "Community Submission",
      "originSource": "community-submission",
      "url": "https://vijomc/",
      "expires": "Siehe Link",
      "distance": "Online",
      "hot": false,
      "isNew": true,
      "votes": 1,
      "priority": 4,
      "qualityScore": 0,
      "pubDate": "2026-05-17T13:33:08.895Z",
      "pubDateSource": "communitySubmission",
      "submittedAt": "2026-05-17T13:33:08.895Z",
      "missingFields": []
    },
    {
      "id": "community:253b1142-8ac5-46bc-b5a9-d63c71dc58ae",
      "submissionId": "253b1142-8ac5-46bc-b5a9-d63c71dc58ae",
      "brand": "OMV",
      "logo": "⛽",
      "title": "viva kaffee eiskaffee",
      "description": "📨 Von der Community eingereicht. Bitte Link, Ort und Ablauf prüfen, bevor der Deal live geht.",
      "type": "rabatt",
      "category": "kaffee",
      "source": "Community Submission",
      "originSource": "community-submission",
      "url": "https://www.omv.at/de/viva/viva-kaffee/viva-eiskaffee",
      "expires": "",
      "distance": "Bitte prüfen",
      "hot": false,
      "isNew": true,
      "votes": 1,
      "priority": 4,
      "qualityScore": 0,
      "pubDate": "2026-05-05T18:39:41.161Z",
      "pubDateSource": "communitySubmission",
      "submittedAt": "2026-05-05T18:39:41.161Z",
      "missingFields": [
        "Ablauf"
      ]
    },
    {
      "id": "community:797eb180-e4c6-4089-b4f4-c4ae888dc26e",
      "submissionId": "797eb180-e4c6-4089-b4f4-c4ae888dc26e",
      "brand": "Instagram",
      "logo": "🎭",
      "title": "Instagram Deal",
      "description": "📨 Von der Community eingereicht. Bitte Link, Ort und Ablauf prüfen, bevor der Deal live geht.",
      "type": "rabatt",
      "category": "kultur",
      "source": "Community Submission",
      "originSource": "community-submission",
      "url": "https://www.instagram.com/reel/DXw6hcCtb19/",
      "expires": "",
      "distance": "Bitte prüfen",
      "hot": false,
      "isNew": true,
      "votes": 1,
      "priority": 4,
      "qualityScore": 0,
      "pubDate": "2026-05-02T06:30:45.321Z",
      "pubDateSource": "communitySubmission",
      "submittedAt": "2026-05-02T06:30:45.321Z",
      "missingFields": [
        "Ablauf"
      ]
    },
    {
      "id": "community:4ef92a64-5860-408f-af8f-ad47f7ead8dc",
      "submissionId": "4ef92a64-5860-408f-af8f-ad47f7ead8dc",
      "brand": "Instagram",
      "logo": "🎭",
      "title": "Instagram Deal",
      "description": "📨 Von der Community eingereicht. Bitte Link, Ort und Ablauf prüfen, bevor der Deal live geht.",
      "type": "rabatt",
      "category": "kultur",
      "source": "Community Submission",
      "originSource": "community-submission",
      "url": "https://www.instagram.com/reel/DXWur6dDL0h/",
      "expires": "",
      "distance": "Bitte prüfen",
      "hot": false,
      "isNew": true,
      "votes": 1,
      "priority": 4,
      "qualityScore": 0,
      "pubDate": "2026-04-21T16:18:03.670Z",
      "pubDateSource": "communitySubmission",
      "submittedAt": "2026-04-21T16:18:03.670Z",
      "missingFields": [
        "Ablauf"
      ]
    }
  ],
  "totalDeals": 15,
  "updatedAt": "2026-06-24T17:24:07.168Z"
}