{
  "generatedAt": "2026-07-22T11:45:16.510Z",
  "summary": {
    "filesConsidered": 28,
    "totalCandidates": 826,
    "uniqueCandidates": 766,
    "distinctCandidates": 794,
    "duplicateClusters": 28,
    "topHealthySources": [
      {
        "sourceKey": "firecrawl2",
        "sourceLabel": "Firecrawl Key 3 - Consumables",
        "healthScore": 100,
        "totalDeals": 6
      },
      {
        "sourceKey": "firecrawl4",
        "sourceLabel": "Firecrawl Key 4 - Instagram Direct",
        "healthScore": 98,
        "totalDeals": 30
      },
      {
        "sourceKey": "food3",
        "sourceLabel": "Firecrawl Key 2 - Food",
        "healthScore": 84,
        "totalDeals": 39
      },
      {
        "sourceKey": "gastro2",
        "sourceLabel": "Firecrawl Key 1 - Gastro",
        "healthScore": 78,
        "totalDeals": 318
      },
      {
        "sourceKey": "joe",
        "sourceLabel": "jö Bonus Club",
        "healthScore": 75,
        "totalDeals": 11
      }
    ],
    "topMissionSources": [
      {
        "sourceKey": "firecrawl4",
        "sourceLabel": "Firecrawl Key 4 - Instagram Direct",
        "missionFitScore": 100,
        "totalDeals": 30
      },
      {
        "sourceKey": "firecrawl2",
        "sourceLabel": "Firecrawl Key 3 - Consumables",
        "missionFitScore": 100,
        "totalDeals": 6
      },
      {
        "sourceKey": "food3",
        "sourceLabel": "Firecrawl Key 2 - Food",
        "missionFitScore": 80,
        "totalDeals": 39
      },
      {
        "sourceKey": "joe",
        "sourceLabel": "jö Bonus Club",
        "missionFitScore": 79,
        "totalDeals": 11
      },
      {
        "sourceKey": "gastro2",
        "sourceLabel": "Firecrawl Key 1 - Gastro",
        "missionFitScore": 68,
        "totalDeals": 318
      }
    ],
    "topCoverageSources": [
      {
        "sourceKey": "gastro2",
        "sourceLabel": "Firecrawl Key 1 - Gastro",
        "coverageScore": 97,
        "totalDeals": 318,
        "fresh1dCount": 111
      },
      {
        "sourceKey": "food3",
        "sourceLabel": "Firecrawl Key 2 - Food",
        "coverageScore": 27,
        "totalDeals": 39,
        "fresh1dCount": 39
      },
      {
        "sourceKey": "firecrawl4",
        "sourceLabel": "Firecrawl Key 4 - Instagram Direct",
        "coverageScore": 27,
        "totalDeals": 30,
        "fresh1dCount": 30
      },
      {
        "sourceKey": "vienna-promo-radar",
        "sourceLabel": "Vienna Promo Radar",
        "coverageScore": 23,
        "totalDeals": 102,
        "fresh1dCount": 0
      },
      {
        "sourceKey": "member-benefits",
        "sourceLabel": "Member Benefits",
        "coverageScore": 22,
        "totalDeals": 46,
        "fresh1dCount": 46
      }
    ],
    "topPrecisionSources": [
      {
        "sourceKey": "firecrawl2",
        "sourceLabel": "Firecrawl Key 3 - Consumables",
        "precisionScore": 100,
        "totalDeals": 6
      },
      {
        "sourceKey": "firecrawl4",
        "sourceLabel": "Firecrawl Key 4 - Instagram Direct",
        "precisionScore": 99,
        "totalDeals": 30
      },
      {
        "sourceKey": "food3",
        "sourceLabel": "Firecrawl Key 2 - Food",
        "precisionScore": 81,
        "totalDeals": 39
      },
      {
        "sourceKey": "gastro2",
        "sourceLabel": "Firecrawl Key 1 - Gastro",
        "precisionScore": 78,
        "totalDeals": 318
      },
      {
        "sourceKey": "firecrawl5",
        "sourceLabel": "Firecrawl Key 5 - Instagram Gastro",
        "precisionScore": 69,
        "totalDeals": 20
      }
    ],
    "topWeightedSources": [
      {
        "sourceKey": "firecrawl4",
        "sourceLabel": "Firecrawl Key 4 - Instagram Direct",
        "sourceWeightScore": 85,
        "totalDeals": 30
      },
      {
        "sourceKey": "firecrawl2",
        "sourceLabel": "Firecrawl Key 3 - Consumables",
        "sourceWeightScore": 83,
        "totalDeals": 6
      },
      {
        "sourceKey": "gastro2",
        "sourceLabel": "Firecrawl Key 1 - Gastro",
        "sourceWeightScore": 79,
        "totalDeals": 318
      },
      {
        "sourceKey": "food3",
        "sourceLabel": "Firecrawl Key 2 - Food",
        "sourceWeightScore": 71,
        "totalDeals": 39
      },
      {
        "sourceKey": "joe",
        "sourceLabel": "jö Bonus Club",
        "sourceWeightScore": 62,
        "totalDeals": 11
      }
    ],
    "topSourcesToFix": [
      {
        "sourceKey": "google",
        "sourceLabel": "Google Deals",
        "healthScore": 0,
        "issues": [
          "liefert aktuell 0 Deals"
        ],
        "sampleTitles": []
      },
      {
        "sourceKey": "instagram-apify",
        "sourceLabel": "instagram-apify",
        "healthScore": 0,
        "issues": [
          "liefert aktuell 0 Deals"
        ],
        "sampleTitles": []
      },
      {
        "sourceKey": "instagram-web",
        "sourceLabel": "Daily Sync Instagram Web",
        "healthScore": 0,
        "issues": [
          "liefert aktuell 0 Deals"
        ],
        "sampleTitles": []
      },
      {
        "sourceKey": "telegram",
        "sourceLabel": "telegram",
        "healthScore": 0,
        "issues": [
          "liefert aktuell 0 Deals"
        ],
        "sampleTitles": []
      },
      {
        "sourceKey": "twitter",
        "sourceLabel": "twitter",
        "healthScore": 0,
        "issues": [
          "liefert aktuell 0 Deals"
        ],
        "sampleTitles": []
      },
      {
        "sourceKey": "instagram-discovery",
        "sourceLabel": "Daily Sync Instagram Discovery",
        "healthScore": 28,
        "issues": [
          "wenige Deals sind frischer als 1 Tag",
          "wenige klare Gratis-/Promo-Signale",
          "Wien-Signal ist zu schwach",
          "hohe Überschneidung mit anderen Quellen"
        ],
        "sampleTitles": [
          "1€ Backfisch-Baguette in Wien - @nordsee_official In allen Wiener Filialen bekommt ih...",
          "New Lebanese Kitchen in Wien - @amaraya.restaurant 📍Breitenfurter Straße 213, 1230 W...",
          "Ausflugsziel 1,5 Stunden von Wien - @erlebnisparadies @heiratenimparadies @suedburgen..."
        ]
      }
    ]
  },
  "sources": [
    {
      "sourceKey": "firecrawl2",
      "file": "deals-pending-firecrawl2.json",
      "sourceLabel": "Firecrawl Key 3 - Consumables",
      "totalDeals": 6,
      "uniqueDeals": 6,
      "duplicateDeals": 0,
      "duplicateAcrossSources": 0,
      "fresh1dCount": 6,
      "fresh7dCount": 6,
      "viennaCount": 6,
      "foodDrinkCount": 6,
      "promoCount": 6,
      "missingUrlCount": 0,
      "sampleTitles": [
        "Wurlitzergasse 87: All-you-can-eat Ramadan Buffet für 26,90 Euro",
        "Barnabitengasse 5: Happy Hour All You Can Eat Hot Pot für 19,90€ statt 29,80€",
        "Franz-Josefs-Kai 49: Student*innen Angebot: All You Can Eat für 9,90€"
      ],
      "uniqueRate": 1,
      "duplicateRate": 0,
      "fresh1dRate": 1,
      "fresh7dRate": 1,
      "viennaRate": 1,
      "foodDrinkRate": 1,
      "promoRate": 1,
      "missingUrlRate": 0,
      "averageQualityScore": 84,
      "topCategories": [
        {
          "value": "essen",
          "count": 6
        }
      ],
      "topTypes": [
        {
          "value": "gratis",
          "count": 5
        },
        {
          "value": "rabatt",
          "count": 1
        }
      ],
      "issues": [],
      "healthScore": 100,
      "missionFitScore": 100,
      "coverageScore": 17,
      "precisionScore": 100,
      "sourceWeightScore": 83
    },
    {
      "sourceKey": "firecrawl4",
      "file": "deals-pending-firecrawl4.json",
      "sourceLabel": "Firecrawl Key 4 - Instagram Direct",
      "totalDeals": 30,
      "uniqueDeals": 28,
      "duplicateDeals": 2,
      "duplicateAcrossSources": 2,
      "fresh1dCount": 30,
      "fresh7dCount": 30,
      "viennaCount": 30,
      "foodDrinkCount": 29,
      "promoCount": 30,
      "missingUrlCount": 0,
      "sampleTitles": [
        "Tokki Korean BBQ: All You Can Eat Mittagsbuffet inklusive gratis Getränk für 14,90 Euro",
        "Sukiyaki: Gratis Getränk zum All-you-can-eat Buffet",
        "XO Grill: Cocktails Buy one, get one free - zwischen 14:00 und 17:00 Uhr, Montag bis Freitag"
      ],
      "uniqueRate": 0.9,
      "duplicateRate": 0.1,
      "fresh1dRate": 1,
      "fresh7dRate": 1,
      "viennaRate": 1,
      "foodDrinkRate": 1,
      "promoRate": 1,
      "missingUrlRate": 0,
      "averageQualityScore": 82.5,
      "topCategories": [
        {
          "value": "essen",
          "count": 15
        },
        {
          "value": "kaffee",
          "count": 14
        },
        {
          "value": "kultur",
          "count": 1
        }
      ],
      "topTypes": [
        {
          "value": "gratis",
          "count": 25
        },
        {
          "value": "bogo",
          "count": 5
        }
      ],
      "issues": [],
      "healthScore": 98,
      "missionFitScore": 100,
      "coverageScore": 27,
      "precisionScore": 99,
      "sourceWeightScore": 85
    },
    {
      "sourceKey": "food3",
      "file": "deals-pending-food3.json",
      "sourceLabel": "Firecrawl Key 2 - Food",
      "totalDeals": 39,
      "uniqueDeals": 36,
      "duplicateDeals": 3,
      "duplicateAcrossSources": 1,
      "fresh1dCount": 39,
      "fresh7dCount": 39,
      "viennaCount": 33,
      "foodDrinkCount": 39,
      "promoCount": 15,
      "missingUrlCount": 0,
      "sampleTitles": [
        "Rollercoaster Restaurant: Essen und Show (Achterbahn-Restaurant)",
        "Hard Rock Cafe Vienna: Speisen und Getränke (alkoholfrei) sowie Merchandise",
        "Mama's Vie: Crêpe mit einem Topping"
      ],
      "uniqueRate": 0.9,
      "duplicateRate": 0,
      "fresh1dRate": 1,
      "fresh7dRate": 1,
      "viennaRate": 0.8,
      "foodDrinkRate": 1,
      "promoRate": 0.4,
      "missingUrlRate": 0,
      "averageQualityScore": 62.8,
      "topCategories": [
        {
          "value": "essen",
          "count": 27
        },
        {
          "value": "kaffee",
          "count": 12
        }
      ],
      "topTypes": [
        {
          "value": "rabatt",
          "count": 25
        },
        {
          "value": "gratis",
          "count": 9
        },
        {
          "value": "bogo",
          "count": 5
        }
      ],
      "issues": [],
      "healthScore": 84,
      "missionFitScore": 80,
      "coverageScore": 27,
      "precisionScore": 81,
      "sourceWeightScore": 71
    },
    {
      "sourceKey": "gastro2",
      "file": "deals-pending-gastro2.json",
      "sourceLabel": "Firecrawl Key 1 - Gastro",
      "totalDeals": 318,
      "uniqueDeals": 298,
      "duplicateDeals": 20,
      "duplicateAcrossSources": 4,
      "fresh1dCount": 111,
      "fresh7dCount": 128,
      "viennaCount": 314,
      "foodDrinkCount": 317,
      "promoCount": 132,
      "missingUrlCount": 0,
      "sampleTitles": [
        "30% Rabatt auf Tapas-Packages und Happy Hour",
        "30% Rabatt auf BBQ Smoker Sharing Menü",
        "30% Rabatt auf nordischer Genuss"
      ],
      "uniqueRate": 0.9,
      "duplicateRate": 0,
      "fresh1dRate": 0.3,
      "fresh7dRate": 0.4,
      "viennaRate": 1,
      "foodDrinkRate": 1,
      "promoRate": 0.4,
      "missingUrlRate": 0,
      "averageQualityScore": 65,
      "topCategories": [
        {
          "value": "essen",
          "count": 317
        },
        {
          "value": "shopping",
          "count": 1
        }
      ],
      "topTypes": [
        {
          "value": "rabatt",
          "count": 194
        },
        {
          "value": "gratis",
          "count": 65
        },
        {
          "value": "bogo",
          "count": 59
        }
      ],
      "issues": [],
      "healthScore": 78,
      "missionFitScore": 68,
      "coverageScore": 97,
      "precisionScore": 78,
      "sourceWeightScore": 79
    },
    {
      "sourceKey": "joe",
      "file": "deals-pending-joe.json",
      "sourceLabel": "jö Bonus Club",
      "totalDeals": 11,
      "uniqueDeals": 11,
      "duplicateDeals": 0,
      "duplicateAcrossSources": 0,
      "fresh1dCount": 11,
      "fresh7dCount": 11,
      "viennaCount": 0,
      "foodDrinkCount": 11,
      "promoCount": 9,
      "missingUrlCount": 0,
      "sampleTitles": [
        "jö Äpp Extrem Aktion bei BILLA",
        "jö Rabattsammler",
        "jö äpp Day"
      ],
      "uniqueRate": 1,
      "duplicateRate": 0,
      "fresh1dRate": 1,
      "fresh7dRate": 1,
      "viennaRate": 0,
      "foodDrinkRate": 1,
      "promoRate": 0.8,
      "missingUrlRate": 0,
      "averageQualityScore": 83.2,
      "topCategories": [
        {
          "value": "supermarkt",
          "count": 5
        },
        {
          "value": "kaffee",
          "count": 4
        },
        {
          "value": "essen",
          "count": 2
        }
      ],
      "topTypes": [
        {
          "value": "gratis",
          "count": 6
        },
        {
          "value": "rabatt",
          "count": 5
        }
      ],
      "issues": [
        "Wien-Signal ist zu schwach"
      ],
      "healthScore": 75,
      "missionFitScore": 79,
      "coverageScore": 13,
      "precisionScore": 68,
      "sourceWeightScore": 62
    },
    {
      "sourceKey": "firecrawl5",
      "file": "deals-pending-firecrawl5.json",
      "sourceLabel": "Firecrawl Key 5 - Instagram Gastro",
      "totalDeals": 20,
      "uniqueDeals": 20,
      "duplicateDeals": 0,
      "duplicateAcrossSources": 0,
      "fresh1dCount": 2,
      "fresh7dCount": 2,
      "viennaCount": 9,
      "foodDrinkCount": 20,
      "promoCount": 14,
      "missingUrlCount": 0,
      "sampleTitles": [
        "Momo Haus: Echtes nepalesisches Essen zum ... Nepali restaurant Berlin, best Nepali food Berlin. Nur solange das Angebot läuft.",
        "ba_haidari: Es gibt übrigens bis 17 Uhr ein Angebot, wie zb Cheeseburger und Fries für 9€.",
        "Zum Stammtisch: SONNTAG Mittagstisch: HEUTE IM ANGEBOT SELBSTGEMACHTE FRIKADELLEN"
      ],
      "uniqueRate": 1,
      "duplicateRate": 0,
      "fresh1dRate": 0.1,
      "fresh7dRate": 0.1,
      "viennaRate": 0.5,
      "foodDrinkRate": 1,
      "promoRate": 0.7,
      "missingUrlRate": 0,
      "averageQualityScore": 80,
      "topCategories": [
        {
          "value": "essen",
          "count": 20
        }
      ],
      "topTypes": [
        {
          "value": "gratis",
          "count": 12
        },
        {
          "value": "gewinnspiel",
          "count": 4
        },
        {
          "value": "rabatt",
          "count": 3
        },
        {
          "value": "bogo",
          "count": 1
        }
      ],
      "issues": [
        "wenige Deals sind frischer als 1 Tag",
        "Wien-Signal ist zu schwach"
      ],
      "healthScore": 72,
      "missionFitScore": 64,
      "coverageScore": 15,
      "precisionScore": 69,
      "sourceWeightScore": 57
    },
    {
      "sourceKey": "tiktok",
      "file": "deals-pending-tiktok.json",
      "sourceLabel": "TikTok Scanner",
      "totalDeals": 4,
      "uniqueDeals": 4,
      "duplicateDeals": 0,
      "duplicateAcrossSources": 0,
      "fresh1dCount": 1,
      "fresh7dCount": 4,
      "viennaCount": 0,
      "foodDrinkCount": 3,
      "promoCount": 4,
      "missingUrlCount": 0,
      "sampleTitles": [
        "Gratis Drink bei Tokki",
        "🍓 Unser Community-Special bis Monatsende",
        "Gratis Eintritt bei @boringenau"
      ],
      "uniqueRate": 1,
      "duplicateRate": 0,
      "fresh1dRate": 0.3,
      "fresh7dRate": 1,
      "viennaRate": 0,
      "foodDrinkRate": 0.8,
      "promoRate": 1,
      "missingUrlRate": 0,
      "averageQualityScore": 69.5,
      "topCategories": [
        {
          "value": "essen",
          "count": 2
        },
        {
          "value": "kaffee",
          "count": 1
        },
        {
          "value": "kultur",
          "count": 1
        }
      ],
      "topTypes": [
        {
          "value": "gratis",
          "count": 4
        }
      ],
      "issues": [
        "Wien-Signal ist zu schwach"
      ],
      "healthScore": 64,
      "missionFitScore": 63,
      "coverageScore": 10,
      "precisionScore": 59,
      "sourceWeightScore": 52
    },
    {
      "sourceKey": "instagram-ai",
      "file": "deals-pending-instagram-ai.json",
      "sourceLabel": "Instagram AI Agent",
      "totalDeals": 3,
      "uniqueDeals": 0,
      "duplicateDeals": 3,
      "duplicateAcrossSources": 3,
      "fresh1dCount": 0,
      "fresh7dCount": 2,
      "viennaCount": 3,
      "foodDrinkCount": 2,
      "promoCount": 2,
      "missingUrlCount": 0,
      "sampleTitles": [
        "Brunch mit Prosecco Free-Flow",
        "All You Can Eat Mittagsbuffet inklusive gratis Getränk",
        "Bei Speisen/Getränken ab 10€ gibt es Gutschein im selben Wert zurück"
      ],
      "uniqueRate": 0,
      "duplicateRate": 1,
      "fresh1dRate": 0,
      "fresh7dRate": 0.7,
      "viennaRate": 1,
      "foodDrinkRate": 0.7,
      "promoRate": 0.7,
      "missingUrlRate": 0,
      "averageQualityScore": 95,
      "topCategories": [
        {
          "value": "food/drink",
          "count": 2
        },
        {
          "value": "essen",
          "count": 1
        }
      ],
      "topTypes": [
        {
          "value": "gratis",
          "count": 2
        },
        {
          "value": "rabatt",
          "count": 1
        }
      ],
      "issues": [
        "wenige Deals sind frischer als 1 Tag",
        "hohe Überschneidung mit anderen Quellen"
      ],
      "healthScore": 53,
      "missionFitScore": 59,
      "coverageScore": 12,
      "precisionScore": 66,
      "sourceWeightScore": 49
    },
    {
      "sourceKey": "member-benefits",
      "file": "deals-pending-member-benefits.json",
      "sourceLabel": "Member Benefits",
      "totalDeals": 46,
      "uniqueDeals": 46,
      "duplicateDeals": 0,
      "duplicateAcrossSources": 0,
      "fresh1dCount": 46,
      "fresh7dCount": 46,
      "viennaCount": 0,
      "foodDrinkCount": 10,
      "promoCount": 20,
      "missingUrlCount": 0,
      "sampleTitles": [
        "1+1 Ticket gratis bei Die Urzeit Chroniken",
        "1+1 Kinoticket gratis bei KinoDonnerstag",
        "1+1 Wrap gratis bei Nordsee"
      ],
      "uniqueRate": 1,
      "duplicateRate": 0,
      "fresh1dRate": 1,
      "fresh7dRate": 1,
      "viennaRate": 0,
      "foodDrinkRate": 0.2,
      "promoRate": 0.4,
      "missingUrlRate": 0,
      "averageQualityScore": 37.1,
      "topCategories": [
        {
          "value": "kultur",
          "count": 15
        },
        {
          "value": "shopping",
          "count": 15
        },
        {
          "value": "essen",
          "count": 6
        },
        {
          "value": "technik",
          "count": 4
        },
        {
          "value": "supermarkt",
          "count": 3
        },
        {
          "value": "fitness",
          "count": 1
        }
      ],
      "topTypes": [
        {
          "value": "rabatt",
          "count": 26
        },
        {
          "value": "bogo",
          "count": 12
        },
        {
          "value": "gratis",
          "count": 8
        }
      ],
      "issues": [
        "geringe Food-/Drink-Relevanz",
        "Wien-Signal ist zu schwach"
      ],
      "healthScore": 52,
      "missionFitScore": 40,
      "coverageScore": 22,
      "precisionScore": 40,
      "sourceWeightScore": 40
    },
    {
      "sourceKey": "church-events",
      "file": "deals-pending-church-events.json",
      "sourceLabel": "Freikirchen Wien",
      "totalDeals": 4,
      "uniqueDeals": 4,
      "duplicateDeals": 0,
      "duplicateAcrossSources": 0,
      "fresh1dCount": 0,
      "fresh7dCount": 4,
      "viennaCount": 4,
      "foodDrinkCount": 0,
      "promoCount": 0,
      "missingUrlCount": 0,
      "sampleTitles": [
        "VCC JesusZentrum Events",
        "ICF Wien Events",
        "CIG Wien Events"
      ],
      "uniqueRate": 1,
      "duplicateRate": 0,
      "fresh1dRate": 0,
      "fresh7dRate": 1,
      "viennaRate": 1,
      "foodDrinkRate": 0,
      "promoRate": 0,
      "missingUrlRate": 0,
      "averageQualityScore": 74,
      "topCategories": [
        {
          "value": "events",
          "count": 4
        }
      ],
      "topTypes": [
        {
          "value": "event",
          "count": 4
        }
      ],
      "issues": [
        "wenige Deals sind frischer als 1 Tag",
        "geringe Food-/Drink-Relevanz",
        "wenige klare Gratis-/Promo-Signale"
      ],
      "healthScore": 50,
      "missionFitScore": 15,
      "coverageScore": 6,
      "precisionScore": 42,
      "sourceWeightScore": 28
    },
    {
      "sourceKey": "church-gemeinde",
      "file": "deals-pending-church-gemeinde.json",
      "sourceLabel": "Freikirchen Wien",
      "totalDeals": 4,
      "uniqueDeals": 4,
      "duplicateDeals": 0,
      "duplicateAcrossSources": 0,
      "fresh1dCount": 0,
      "fresh7dCount": 4,
      "viennaCount": 4,
      "foodDrinkCount": 0,
      "promoCount": 0,
      "missingUrlCount": 0,
      "sampleTitles": [
        "VCC JesusZentrum",
        "ICF Wien",
        "CIG Wien"
      ],
      "uniqueRate": 1,
      "duplicateRate": 0,
      "fresh1dRate": 0,
      "fresh7dRate": 1,
      "viennaRate": 1,
      "foodDrinkRate": 0,
      "promoRate": 0,
      "missingUrlRate": 0,
      "averageQualityScore": 72,
      "topCategories": [
        {
          "value": "kirche",
          "count": 3
        },
        {
          "value": "gottesdienste",
          "count": 1
        }
      ],
      "topTypes": [
        {
          "value": "info",
          "count": 4
        }
      ],
      "issues": [
        "wenige Deals sind frischer als 1 Tag",
        "geringe Food-/Drink-Relevanz",
        "wenige klare Gratis-/Promo-Signale"
      ],
      "healthScore": 50,
      "missionFitScore": 15,
      "coverageScore": 6,
      "precisionScore": 42,
      "sourceWeightScore": 28
    },
    {
      "sourceKey": "church-gottesdienste",
      "file": "deals-pending-church-gottesdienste.json",
      "sourceLabel": "Freikirchen Wien",
      "totalDeals": 4,
      "uniqueDeals": 4,
      "duplicateDeals": 0,
      "duplicateAcrossSources": 0,
      "fresh1dCount": 0,
      "fresh7dCount": 4,
      "viennaCount": 4,
      "foodDrinkCount": 0,
      "promoCount": 0,
      "missingUrlCount": 0,
      "sampleTitles": [
        "VCC JesusZentrum Gottesdienste",
        "ICF Wien Gottesdienste",
        "CIG Wien Gottesdienste"
      ],
      "uniqueRate": 1,
      "duplicateRate": 0,
      "fresh1dRate": 0,
      "fresh7dRate": 1,
      "viennaRate": 1,
      "foodDrinkRate": 0,
      "promoRate": 0,
      "missingUrlRate": 0,
      "averageQualityScore": 78,
      "topCategories": [
        {
          "value": "gottesdienste",
          "count": 4
        }
      ],
      "topTypes": [
        {
          "value": "info",
          "count": 4
        }
      ],
      "issues": [
        "wenige Deals sind frischer als 1 Tag",
        "geringe Food-/Drink-Relevanz",
        "wenige klare Gratis-/Promo-Signale"
      ],
      "healthScore": 50,
      "missionFitScore": 15,
      "coverageScore": 6,
      "precisionScore": 42,
      "sourceWeightScore": 28
    },
    {
      "sourceKey": "community",
      "file": "deals-pending-community.json",
      "sourceLabel": "Community Submission",
      "totalDeals": 39,
      "uniqueDeals": 36,
      "duplicateDeals": 3,
      "duplicateAcrossSources": 1,
      "fresh1dCount": 0,
      "fresh7dCount": 0,
      "viennaCount": 0,
      "foodDrinkCount": 19,
      "promoCount": 32,
      "missingUrlCount": 0,
      "sampleTitles": [
        "Gratis 2. Schnitzel mit Schulzeugnis",
        "Gratis Eis",
        "Gratis Energy Drink 9L"
      ],
      "uniqueRate": 0.9,
      "duplicateRate": 0,
      "fresh1dRate": 0,
      "fresh7dRate": 0,
      "viennaRate": 0,
      "foodDrinkRate": 0.5,
      "promoRate": 0.8,
      "missingUrlRate": 0,
      "averageQualityScore": 0,
      "topCategories": [
        {
          "value": "shopping",
          "count": 15
        },
        {
          "value": "essen",
          "count": 13
        },
        {
          "value": "kaffee",
          "count": 6
        },
        {
          "value": "kultur",
          "count": 2
        },
        {
          "value": "wien",
          "count": 2
        },
        {
          "value": "kirche",
          "count": 1
        }
      ],
      "topTypes": [
        {
          "value": "rabatt",
          "count": 22
        },
        {
          "value": "gratis",
          "count": 12
        },
        {
          "value": "bogo",
          "count": 4
        },
        {
          "value": "freebie",
          "count": 1
        }
      ],
      "issues": [
        "wenige Deals sind frischer als 1 Tag",
        "Wien-Signal ist zu schwach"
      ],
      "healthScore": 49,
      "missionFitScore": 40,
      "coverageScore": 14,
      "precisionScore": 44,
      "sourceWeightScore": 38
    },
    {
      "sourceKey": "gemeinde",
      "file": "deals-pending-gemeinde.json",
      "sourceLabel": "Kirchen Verzeichnis",
      "totalDeals": 34,
      "uniqueDeals": 34,
      "duplicateDeals": 0,
      "duplicateAcrossSources": 0,
      "fresh1dCount": 0,
      "fresh7dCount": 0,
      "viennaCount": 0,
      "foodDrinkCount": 0,
      "promoCount": 34,
      "missingUrlCount": 0,
      "sampleTitles": [
        "⭐ Gemeinde",
        "⭐ Gemeinde",
        "⭐ Gemeinde"
      ],
      "uniqueRate": 1,
      "duplicateRate": 0,
      "fresh1dRate": 0,
      "fresh7dRate": 0,
      "viennaRate": 0,
      "foodDrinkRate": 0,
      "promoRate": 1,
      "missingUrlRate": 0,
      "averageQualityScore": 50,
      "topCategories": [
        {
          "value": "kirche",
          "count": 34
        }
      ],
      "topTypes": [
        {
          "value": "gratis",
          "count": 34
        }
      ],
      "issues": [
        "wenige Deals sind frischer als 1 Tag",
        "geringe Food-/Drink-Relevanz",
        "Wien-Signal ist zu schwach"
      ],
      "healthScore": 44,
      "missionFitScore": 28,
      "coverageScore": 12,
      "precisionScore": 36,
      "sourceWeightScore": 31
    },
    {
      "sourceKey": "freikirchen",
      "file": "deals-pending-freikirchen.json",
      "sourceLabel": "Freikirchen Wien",
      "totalDeals": 33,
      "uniqueDeals": 33,
      "duplicateDeals": 0,
      "duplicateAcrossSources": 0,
      "fresh1dCount": 0,
      "fresh7dCount": 0,
      "viennaCount": 0,
      "foodDrinkCount": 0,
      "promoCount": 33,
      "missingUrlCount": 0,
      "sampleTitles": [
        "Jesus Zentrum Wien Gottesdienst",
        "Hillsong Wien Gottesdienst",
        "City Church Wien Gottesdienst"
      ],
      "uniqueRate": 1,
      "duplicateRate": 0,
      "fresh1dRate": 0,
      "fresh7dRate": 0,
      "viennaRate": 0,
      "foodDrinkRate": 0,
      "promoRate": 1,
      "missingUrlRate": 0,
      "averageQualityScore": 70,
      "topCategories": [
        {
          "value": "gottesdienste",
          "count": 33
        }
      ],
      "topTypes": [
        {
          "value": "gratis",
          "count": 33
        }
      ],
      "issues": [
        "wenige Deals sind frischer als 1 Tag",
        "geringe Food-/Drink-Relevanz",
        "Wien-Signal ist zu schwach"
      ],
      "healthScore": 44,
      "missionFitScore": 28,
      "coverageScore": 12,
      "precisionScore": 36,
      "sourceWeightScore": 31
    },
    {
      "sourceKey": "gottesdienste",
      "file": "deals-pending-gottesdienste.json",
      "sourceLabel": "Kirchen Gottesdienste",
      "totalDeals": 30,
      "uniqueDeals": 30,
      "duplicateDeals": 0,
      "duplicateAcrossSources": 0,
      "fresh1dCount": 0,
      "fresh7dCount": 0,
      "viennaCount": 0,
      "foodDrinkCount": 0,
      "promoCount": 30,
      "missingUrlCount": 0,
      "sampleTitles": [
        "⏰ Samstag 17:00 Uhr",
        "⏰ Sonntag 10:00 & 18:00 Uhr",
        "⏰ Mo-So 06:00-22:00 Uhr"
      ],
      "uniqueRate": 1,
      "duplicateRate": 0,
      "fresh1dRate": 0,
      "fresh7dRate": 0,
      "viennaRate": 0,
      "foodDrinkRate": 0,
      "promoRate": 1,
      "missingUrlRate": 0,
      "averageQualityScore": 50,
      "topCategories": [
        {
          "value": "gottesdienste",
          "count": 30
        }
      ],
      "topTypes": [
        {
          "value": "gratis",
          "count": 30
        }
      ],
      "issues": [
        "wenige Deals sind frischer als 1 Tag",
        "geringe Food-/Drink-Relevanz",
        "Wien-Signal ist zu schwach"
      ],
      "healthScore": 44,
      "missionFitScore": 28,
      "coverageScore": 11,
      "precisionScore": 36,
      "sourceWeightScore": 31
    },
    {
      "sourceKey": "gutscheine",
      "file": "deals-pending-gutscheine.json",
      "sourceLabel": "Gutscheine.at",
      "totalDeals": 24,
      "uniqueDeals": 24,
      "duplicateDeals": 0,
      "duplicateAcrossSources": 0,
      "fresh1dCount": 24,
      "fresh7dCount": 24,
      "viennaCount": 0,
      "foodDrinkCount": 3,
      "promoCount": 1,
      "missingUrlCount": 0,
      "sampleTitles": [
        "40€ TUI Coupon für Top-Reiseziele",
        "Summer Sale: Bis zu 50% Rabatt + Gratisversand",
        "300€ Frühbucher -Ermäßigung auf Karibikreisen"
      ],
      "uniqueRate": 1,
      "duplicateRate": 0,
      "fresh1dRate": 1,
      "fresh7dRate": 1,
      "viennaRate": 0,
      "foodDrinkRate": 0.1,
      "promoRate": 0,
      "missingUrlRate": 0,
      "averageQualityScore": 55.2,
      "topCategories": [
        {
          "value": "shopping",
          "count": 18
        },
        {
          "value": "beauty",
          "count": 2
        },
        {
          "value": "essen",
          "count": 2
        },
        {
          "value": "kaffee",
          "count": 1
        },
        {
          "value": "reisen",
          "count": 1
        }
      ],
      "topTypes": [
        {
          "value": "rabatt",
          "count": 23
        },
        {
          "value": "freebie",
          "count": 1
        }
      ],
      "issues": [
        "geringe Food-/Drink-Relevanz",
        "wenige klare Gratis-/Promo-Signale",
        "Wien-Signal ist zu schwach"
      ],
      "healthScore": 44,
      "missionFitScore": 26,
      "coverageScore": 10,
      "precisionScore": 28,
      "sourceWeightScore": 28
    },
    {
      "sourceKey": "events",
      "file": "deals-pending-events.json",
      "sourceLabel": "Kirchen Events",
      "totalDeals": 35,
      "uniqueDeals": 35,
      "duplicateDeals": 0,
      "duplicateAcrossSources": 0,
      "fresh1dCount": 0,
      "fresh7dCount": 0,
      "viennaCount": 0,
      "foodDrinkCount": 0,
      "promoCount": 35,
      "missingUrlCount": 2,
      "sampleTitles": [
        "Christliches Festival für junge Menschen",
        "Weihnachtsmarkt",
        "Großes Open-Air Festival"
      ],
      "uniqueRate": 1,
      "duplicateRate": 0,
      "fresh1dRate": 0,
      "fresh7dRate": 0,
      "viennaRate": 0,
      "foodDrinkRate": 0,
      "promoRate": 1,
      "missingUrlRate": 0.1,
      "averageQualityScore": 50,
      "topCategories": [
        {
          "value": "kirche",
          "count": 34
        },
        {
          "value": "kultur",
          "count": 1
        }
      ],
      "topTypes": [
        {
          "value": "gratis",
          "count": 35
        }
      ],
      "issues": [
        "wenige Deals sind frischer als 1 Tag",
        "geringe Food-/Drink-Relevanz",
        "Wien-Signal ist zu schwach"
      ],
      "healthScore": 43,
      "missionFitScore": 28,
      "coverageScore": 12,
      "precisionScore": 35,
      "sourceWeightScore": 30
    },
    {
      "sourceKey": "vienna-promo-radar",
      "file": "deals-pending-vienna-promo-radar.json",
      "sourceLabel": "Vienna Promo Radar",
      "totalDeals": 102,
      "uniqueDeals": 96,
      "duplicateDeals": 6,
      "duplicateAcrossSources": 0,
      "fresh1dCount": 0,
      "fresh7dCount": 1,
      "viennaCount": 0,
      "foodDrinkCount": 37,
      "promoCount": 27,
      "missingUrlCount": 0,
      "sampleTitles": [
        "GRATIS: Gratis-Getränk-Aktion: Starbucks eröffnet neuen Standort in Wien",
        "GRATIS: Gratis-Getränk-Aktion: Starbucks eröffnet neuen Standort in Wien",
        "GRATIS: Salzburg lockt zur Neutorsperre mit 33-Euro-Klimaticket und Gratis-Tageskarten"
      ],
      "uniqueRate": 0.9,
      "duplicateRate": 0,
      "fresh1dRate": 0,
      "fresh7dRate": 0,
      "viennaRate": 0,
      "foodDrinkRate": 0.4,
      "promoRate": 0.3,
      "missingUrlRate": 0,
      "averageQualityScore": 43.2,
      "topCategories": [
        {
          "value": "reisen",
          "count": 36
        },
        {
          "value": "kaffee",
          "count": 24
        },
        {
          "value": "essen",
          "count": 12
        },
        {
          "value": "beauty",
          "count": 10
        },
        {
          "value": "fitness",
          "count": 9
        },
        {
          "value": "shopping",
          "count": 6
        }
      ],
      "topTypes": [
        {
          "value": "rabatt",
          "count": 77
        },
        {
          "value": "gratis",
          "count": 24
        },
        {
          "value": "freebie",
          "count": 1
        }
      ],
      "issues": [
        "wenige Deals sind frischer als 1 Tag",
        "geringe Food-/Drink-Relevanz",
        "wenige klare Gratis-/Promo-Signale",
        "Wien-Signal ist zu schwach"
      ],
      "healthScore": 39,
      "missionFitScore": 22,
      "coverageScore": 23,
      "precisionScore": 30,
      "sourceWeightScore": 29
    },
    {
      "sourceKey": "instagram-verified",
      "file": "deals-pending-instagram-verified.json",
      "sourceLabel": "Instagram",
      "totalDeals": 12,
      "uniqueDeals": 0,
      "duplicateDeals": 12,
      "duplicateAcrossSources": 12,
      "fresh1dCount": 0,
      "fresh7dCount": 2,
      "viennaCount": 3,
      "foodDrinkCount": 11,
      "promoCount": 3,
      "missingUrlCount": 0,
      "sampleTitles": [
        "1€ Backfisch-Baguette in Wien - @nordsee_official In allen Wiener Filialen bekommt ih...",
        "Brunch mit Prosecco Free-Flow",
        "All You Can Eat Mittagsbuffet inklusive gratis Getränk"
      ],
      "uniqueRate": 0,
      "duplicateRate": 1,
      "fresh1dRate": 0,
      "fresh7dRate": 0.2,
      "viennaRate": 0.3,
      "foodDrinkRate": 0.9,
      "promoRate": 0.3,
      "missingUrlRate": 0,
      "averageQualityScore": 77.8,
      "topCategories": [
        {
          "value": "essen",
          "count": 10
        },
        {
          "value": "food/drink",
          "count": 2
        }
      ],
      "topTypes": [
        {
          "value": "rabatt",
          "count": 10
        },
        {
          "value": "gratis",
          "count": 2
        }
      ],
      "issues": [
        "wenige Deals sind frischer als 1 Tag",
        "wenige klare Gratis-/Promo-Signale",
        "Wien-Signal ist zu schwach",
        "hohe Überschneidung mit anderen Quellen"
      ],
      "healthScore": 35,
      "missionFitScore": 44,
      "coverageScore": 9,
      "precisionScore": 43,
      "sourceWeightScore": 34
    },
    {
      "sourceKey": "power",
      "file": "deals-pending-power.json",
      "sourceLabel": "Power Scraper",
      "totalDeals": 6,
      "uniqueDeals": 4,
      "duplicateDeals": 2,
      "duplicateAcrossSources": 0,
      "fresh1dCount": 6,
      "fresh7dCount": 6,
      "viennaCount": 0,
      "foodDrinkCount": 0,
      "promoCount": 0,
      "missingUrlCount": 0,
      "sampleTitles": [
        "Preise & Angebote",
        "Exklusivangebote",
        "Marketing / Sales"
      ],
      "uniqueRate": 0.7,
      "duplicateRate": 0,
      "fresh1dRate": 1,
      "fresh7dRate": 1,
      "viennaRate": 0,
      "foodDrinkRate": 0,
      "promoRate": 0,
      "missingUrlRate": 0,
      "averageQualityScore": 38,
      "topCategories": [
        {
          "value": "freizeit",
          "count": 3
        },
        {
          "value": "reisen",
          "count": 3
        }
      ],
      "topTypes": [
        {
          "value": "rabatt",
          "count": 6
        }
      ],
      "issues": [
        "geringe Food-/Drink-Relevanz",
        "wenige klare Gratis-/Promo-Signale",
        "Wien-Signal ist zu schwach"
      ],
      "healthScore": 35,
      "missionFitScore": 22,
      "coverageScore": 2,
      "precisionScore": 26,
      "sourceWeightScore": 22
    },
    {
      "sourceKey": "flights",
      "file": "deals-pending-flights.json",
      "sourceLabel": "Flights Vienna",
      "totalDeals": 13,
      "uniqueDeals": 13,
      "duplicateDeals": 0,
      "duplicateAcrossSources": 0,
      "fresh1dCount": 0,
      "fresh7dCount": 13,
      "viennaCount": 0,
      "foodDrinkCount": 0,
      "promoCount": 0,
      "missingUrlCount": 0,
      "sampleTitles": [
        "Hin & zurück nach Krakow ab €33.98",
        "Hin & zurück nach Pula ab €39.98",
        "Hin & zurück nach Bucharest ab €45.27"
      ],
      "uniqueRate": 1,
      "duplicateRate": 0,
      "fresh1dRate": 0,
      "fresh7dRate": 1,
      "viennaRate": 0,
      "foodDrinkRate": 0,
      "promoRate": 0,
      "missingUrlRate": 0,
      "averageQualityScore": 74.8,
      "topCategories": [
        {
          "value": "reisen",
          "count": 13
        }
      ],
      "topTypes": [
        {
          "value": "rabatt",
          "count": 13
        }
      ],
      "issues": [
        "wenige Deals sind frischer als 1 Tag",
        "geringe Food-/Drink-Relevanz",
        "wenige klare Gratis-/Promo-Signale",
        "Wien-Signal ist zu schwach"
      ],
      "healthScore": 28,
      "missionFitScore": 0,
      "coverageScore": 3,
      "precisionScore": 14,
      "sourceWeightScore": 11
    },
    {
      "sourceKey": "instagram-discovery",
      "file": "deals-pending-instagram-discovery.json",
      "sourceLabel": "Daily Sync Instagram Discovery",
      "totalDeals": 9,
      "uniqueDeals": 0,
      "duplicateDeals": 9,
      "duplicateAcrossSources": 9,
      "fresh1dCount": 0,
      "fresh7dCount": 0,
      "viennaCount": 0,
      "foodDrinkCount": 9,
      "promoCount": 1,
      "missingUrlCount": 0,
      "sampleTitles": [
        "1€ Backfisch-Baguette in Wien - @nordsee_official In allen Wiener Filialen bekommt ih...",
        "New Lebanese Kitchen in Wien - @amaraya.restaurant 📍Breitenfurter Straße 213, 1230 W...",
        "Ausflugsziel 1,5 Stunden von Wien - @erlebnisparadies @heiratenimparadies @suedburgen..."
      ],
      "uniqueRate": 0,
      "duplicateRate": 1,
      "fresh1dRate": 0,
      "fresh7dRate": 0,
      "viennaRate": 0,
      "foodDrinkRate": 1,
      "promoRate": 0.1,
      "missingUrlRate": 0,
      "averageQualityScore": 72.1,
      "topCategories": [
        {
          "value": "essen",
          "count": 9
        }
      ],
      "topTypes": [
        {
          "value": "rabatt",
          "count": 9
        }
      ],
      "issues": [
        "wenige Deals sind frischer als 1 Tag",
        "wenige klare Gratis-/Promo-Signale",
        "Wien-Signal ist zu schwach",
        "hohe Überschneidung mit anderen Quellen"
      ],
      "healthScore": 28,
      "missionFitScore": 38,
      "coverageScore": 7,
      "precisionScore": 32,
      "sourceWeightScore": 28
    },
    {
      "sourceKey": "google",
      "file": "deals-pending-google.json",
      "sourceLabel": "Google Deals",
      "totalDeals": 0,
      "uniqueDeals": 0,
      "duplicateDeals": 0,
      "duplicateAcrossSources": 0,
      "fresh1dCount": 0,
      "fresh7dCount": 0,
      "viennaCount": 0,
      "foodDrinkCount": 0,
      "promoCount": 0,
      "missingUrlCount": 0,
      "sampleTitles": [],
      "uniqueRate": 0,
      "duplicateRate": 0,
      "fresh1dRate": 0,
      "fresh7dRate": 0,
      "viennaRate": 0,
      "foodDrinkRate": 0,
      "promoRate": 0,
      "missingUrlRate": 0,
      "averageQualityScore": 0,
      "topCategories": [],
      "topTypes": [],
      "issues": [
        "liefert aktuell 0 Deals"
      ],
      "healthScore": 0,
      "missionFitScore": 0,
      "coverageScore": 0,
      "precisionScore": 0,
      "sourceWeightScore": 0
    },
    {
      "sourceKey": "instagram-apify",
      "file": "deals-pending-instagram-apify.json",
      "sourceLabel": "instagram-apify",
      "totalDeals": 0,
      "uniqueDeals": 0,
      "duplicateDeals": 0,
      "duplicateAcrossSources": 0,
      "fresh1dCount": 0,
      "fresh7dCount": 0,
      "viennaCount": 0,
      "foodDrinkCount": 0,
      "promoCount": 0,
      "missingUrlCount": 0,
      "sampleTitles": [],
      "uniqueRate": 0,
      "duplicateRate": 0,
      "fresh1dRate": 0,
      "fresh7dRate": 0,
      "viennaRate": 0,
      "foodDrinkRate": 0,
      "promoRate": 0,
      "missingUrlRate": 0,
      "averageQualityScore": 0,
      "topCategories": [],
      "topTypes": [],
      "issues": [
        "liefert aktuell 0 Deals"
      ],
      "healthScore": 0,
      "missionFitScore": 0,
      "coverageScore": 0,
      "precisionScore": 0,
      "sourceWeightScore": 0
    },
    {
      "sourceKey": "instagram-web",
      "file": "deals-pending-instagram-web.json",
      "sourceLabel": "Daily Sync Instagram Web",
      "totalDeals": 0,
      "uniqueDeals": 0,
      "duplicateDeals": 0,
      "duplicateAcrossSources": 0,
      "fresh1dCount": 0,
      "fresh7dCount": 0,
      "viennaCount": 0,
      "foodDrinkCount": 0,
      "promoCount": 0,
      "missingUrlCount": 0,
      "sampleTitles": [],
      "uniqueRate": 0,
      "duplicateRate": 0,
      "fresh1dRate": 0,
      "fresh7dRate": 0,
      "viennaRate": 0,
      "foodDrinkRate": 0,
      "promoRate": 0,
      "missingUrlRate": 0,
      "averageQualityScore": 0,
      "topCategories": [],
      "topTypes": [],
      "issues": [
        "liefert aktuell 0 Deals"
      ],
      "healthScore": 0,
      "missionFitScore": 0,
      "coverageScore": 0,
      "precisionScore": 0,
      "sourceWeightScore": 0
    },
    {
      "sourceKey": "telegram",
      "file": "deals-pending-telegram.json",
      "sourceLabel": "telegram",
      "totalDeals": 0,
      "uniqueDeals": 0,
      "duplicateDeals": 0,
      "duplicateAcrossSources": 0,
      "fresh1dCount": 0,
      "fresh7dCount": 0,
      "viennaCount": 0,
      "foodDrinkCount": 0,
      "promoCount": 0,
      "missingUrlCount": 0,
      "sampleTitles": [],
      "uniqueRate": 0,
      "duplicateRate": 0,
      "fresh1dRate": 0,
      "fresh7dRate": 0,
      "viennaRate": 0,
      "foodDrinkRate": 0,
      "promoRate": 0,
      "missingUrlRate": 0,
      "averageQualityScore": 0,
      "topCategories": [],
      "topTypes": [],
      "issues": [
        "liefert aktuell 0 Deals"
      ],
      "healthScore": 0,
      "missionFitScore": 0,
      "coverageScore": 0,
      "precisionScore": 0,
      "sourceWeightScore": 0
    },
    {
      "sourceKey": "twitter",
      "file": "deals-pending-twitter.json",
      "sourceLabel": "twitter",
      "totalDeals": 0,
      "uniqueDeals": 0,
      "duplicateDeals": 0,
      "duplicateAcrossSources": 0,
      "fresh1dCount": 0,
      "fresh7dCount": 0,
      "viennaCount": 0,
      "foodDrinkCount": 0,
      "promoCount": 0,
      "missingUrlCount": 0,
      "sampleTitles": [],
      "uniqueRate": 0,
      "duplicateRate": 0,
      "fresh1dRate": 0,
      "fresh7dRate": 0,
      "viennaRate": 0,
      "foodDrinkRate": 0,
      "promoRate": 0,
      "missingUrlRate": 0,
      "averageQualityScore": 0,
      "topCategories": [],
      "topTypes": [],
      "issues": [
        "liefert aktuell 0 Deals"
      ],
      "healthScore": 0,
      "missionFitScore": 0,
      "coverageScore": 0,
      "precisionScore": 0,
      "sourceWeightScore": 0
    }
  ]
}
